neuralfilter/__init__.py
neuralfilter/attention.py
neuralfilter/utils.py
neuralfilter-0.1.9.dist-info/METADATA
neuralfilter-0.1.9.dist-info/WHEEL
neuralfilter-0.1.9.dist-info/top_level.txt
neuralfilter-0.1.9.dist-info/RECORD
