Metadata-Version: 2.1
Name: neuralfilter
Version: 0.1.9
Summary: neural attention filter
Home-page: UNKNOWN
Author: YeongHyeon Park
Author-email: young200405@gmail.com
License: UNKNOWN
Keywords: neural-filter
Platform: UNKNOWN
Classifier: Programming Language :: Python :: 3
Requires-Python: >=3
Requires-Dist: numpy
Requires-Dist: scipy
Requires-Dist: tensorflow
